pise/__init__.py
pise/analysis/get_composition_info.py
pise/analysis/get_final_energy.py
pise/analysis/plot_band.py
pise/cli/init_env.py
pise/cli/main.py
pise/config/environment.py
pise/flow/concrete/unitcell_flow.py
pise/jobs/abstract/job_base.py
pise/jobs/abstract/job_convergence.py
pise/jobs/abstract/job_input.py
pise/jobs/abstract/job_script.py
pise/jobs/abstract/job_status.py
pise/jobs/abstract/job_submitter.py
pise/jobs/concrete/band.py
pise/jobs/concrete/opt.py
pise/utils/io.py
pise/utils/logger.py
pise-0.1.0.dist-info/METADATA
pise-0.1.0.dist-info/WHEEL
pise-0.1.0.dist-info/entry_points.txt
pise-0.1.0.dist-info/RECORD
